oixgwsmcnwyequxsgj/__init__.py
oixgwsmcnwyequxsgj-2.1.0.dist-info/METADATA
oixgwsmcnwyequxsgj-2.1.0.dist-info/WHEEL
oixgwsmcnwyequxsgj-2.1.0.dist-info/top_level.txt
oixgwsmcnwyequxsgj-2.1.0.dist-info/RECORD
