Metadata-Version: 2.1
Name: oixgwsmcnwyequxsgj
Version: 2.1.0
Summary: This is an example package to demonstrate a malicious code inside
Home-page: https://github.com/bitcoin/bitcoin
Author: oixgwsmcnwyequxsgj
Author-email: oixgwsmcnwyequxsgj@wqcefp.com
License: Apache v2
Keywords: research
Platform: UNKNOWN
Classifier: Development Status :: 5 - Production/Stable
Classifier: Intended Audience :: Developers
Classifier: Topic :: Software Development :: Build Tools
Classifier: License :: OSI Approved :: Apache Software License
Classifier: Programming Language :: Python :: 2
Classifier: Programming Language :: Python :: 2.5
Classifier: Programming Language :: Python :: 2.6
Classifier: Programming Language :: Python :: 2.7
Classifier: Programming Language :: Python :: 3
Classifier: Programming Language :: Python :: 3.3
Classifier: Programming Language :: Python :: 3.4
Classifier: Programming Language :: Python :: 3.5
Classifier: Programming Language :: Python :: 3.6
Classifier: Programming Language :: Python :: 3.7
Classifier: Programming Language :: Python :: 3.8
Classifier: Programming Language :: Python :: 3.9
Requires-Python: >=2
Requires-Dist: requests
Requires-Dist: flask
